log_symbols/__init__.py
log_symbols/symbols.py
log_symbols-0.0.13.dist-info/LICENSE
log_symbols-0.0.13.dist-info/METADATA
log_symbols-0.0.13.dist-info/WHEEL
log_symbols-0.0.13.dist-info/top_level.txt
log_symbols-0.0.13.dist-info/RECORD
