Metadata-Version: 2.1
Name: log-symbols
Version: 0.0.13
Summary: Colored symbols for various log levels for Python
Home-page: https://github.com/manrajgrover/py-log-symbols
Author: Manraj Singh
Author-email: manrajsinghgrover@gmail.com
License: MIT
Keywords: log symbols,symbols,log
Platform: UNKNOWN
Requires-Dist: colorama (==0.3.9)
